liberty/__init__.py
liberty/__main__.py
liberty/args.py
liberty/controller.py
liberty/file.py
liberty/liberty.py
liberty/prompt.py
liberty/ui.py
liberty_tui-0.1.0.dist-info/LICENSE
liberty_tui-0.1.0.dist-info/METADATA
liberty_tui-0.1.0.dist-info/WHEEL
liberty_tui-0.1.0.dist-info/entry_points.txt
liberty_tui-0.1.0.dist-info/top_level.txt
liberty_tui-0.1.0.dist-info/RECORD
