Metadata-Version: 2.1
Name: liberty-tui
Version: 0.1.0
Summary: A spaced-repetition TUI for free-response active recall.
Home-page: https://github.com/kewbish/liberty
Author: Emilie Ma (kewbish)
Author-email: kewbish@gmail.com
License: MIT License
Platform: UNKNOWN
Classifier: Development Status :: 1 - Planning
Classifier: License :: OSI Approved :: MIT License
Classifier: Programming Language :: Python :: 3
Classifier: Programming Language :: Python :: 3.9
Requires-Python: >=3
License-File: LICENSE
Requires-Dist: urwid
